{"is_source_file": true, "format": "JavaScript", "description": "This file exports a list of video metadata objects related to Coursera courses and videos, including details such as title, URL, channel, views, upload date, duration, and description. It also has a function to retrieve a video by its ID.", "external_files": [], "external_methods": [], "published": ["videos", "getVideoById"], "classes": [], "methods": [{"name": "getVideoById(id)", "description": "Function to find and return a video object by its ID.", "scope": "", "scopeKind": ""}], "calls": ["getVideoById"], "search-terms": ["videos", "video metadata", "YouTube links", "Coursera courses", "video list", "video data", "getVideoById"], "state": 2, "file_id": 13, "knowledge_revision": 96, "git_revision": "38cbb8b9925d95e648a4c03f9a493e006db23453", "revision_history": [{"27": ""}, {"48": "6b2278403c1ab4842927f1a7f7164fb81f6728f2"}, {"55": "2658c0a2af3f192b104424cb421833303756fb3d"}, {"85": "d3b17f7bc93b30981cd6a0c918d41bfae68b4e2a"}, {"96": "38cbb8b9925d95e648a4c03f9a493e006db23453"}], "ctags": [{"_type": "tag", "name": "getVideoById", "path": "/home/kavia/workspace/code-generation/streamview-221852-221861/video_streamer_frontend/src/data/videos.js", "pattern": "/^export function getVideoById(id) {$/", "language": "JavaScript", "kind": "function", "signature": "(id)"}, {"_type": "tag", "name": "videos", "path": "/home/kavia/workspace/code-generation/streamview-221852-221861/video_streamer_frontend/src/data/videos.js", "pattern": "/^export const videos = [$/", "language": "JavaScript", "kind": "constant"}], "hash": "a04baf475afdde7d08bec5ba0b96b497", "format-version": 4, "code-base-name": "video_streamer_frontend", "filename": "video_streamer_frontend/src/data/videos.js"}